telebaka_channel_helper/__init__.py
telebaka_channel_helper/admin.py
telebaka_channel_helper/bot.py
telebaka_channel_helper/models.py
telebaka_channel_helper/tasks.py
telebaka_channel_helper/migrations/0001_initial.py
telebaka_channel_helper/migrations/__init__.py
telebaka_channel_helper-0.1.13.dist-info/METADATA
telebaka_channel_helper-0.1.13.dist-info/WHEEL
telebaka_channel_helper-0.1.13.dist-info/top_level.txt
telebaka_channel_helper-0.1.13.dist-info/RECORD
